latex_generator_2/__init__.py
latex_generator_2/latex_gen_12.py
latex_generator_2-0.0.0.dist-info/LICENSE.txt
latex_generator_2-0.0.0.dist-info/METADATA
latex_generator_2-0.0.0.dist-info/WHEEL
latex_generator_2-0.0.0.dist-info/top_level.txt
latex_generator_2-0.0.0.dist-info/RECORD
