Metadata-Version: 2.1
Name: latex-generator-2
Version: 0.0.0
Summary: Functions for generating LaTeX code
Author: esaulvn
License-File: LICENSE.txt
